Workbook

Sheet Summary
A1: Funding Strategy Summary
A2: Totals recalculate from the Register sheet. Season One = 2027 event; Season Two = 2028; Partner route = needs a charity or arts partner.
A4: Season | B4: Sources | C4: Total ask ($) | D4: Expected ($)
A5: Season One | B5: =COUNTIF(Register!$E$5:$E$30,A5) -> 16 | C5: =SUMIF(Register!$E$5:$E$30,$A5,Register!$H$5:$H$30) -> 238816 | D5: =SUMIF(Register!$E$5:$E$30,$A5,Register!$L$5:$L$30) -> 52761.96
A6: Season Two | B6: =COUNTIF(Register!$E$5:$E$30,A6) -> 3 | C6: =SUMIF(Register!$E$5:$E$30,$A6,Register!$H$5:$H$30) -> 275000 | D6: =SUMIF(Register!$E$5:$E$30,$A6,Register!$L$5:$L$30) -> 30750
A7: Partner route | B7: =COUNTIF(Register!$E$5:$E$30,A7) -> 7 | C7: =SUMIF(Register!$E$5:$E$30,$A7,Register!$H$5:$H$30) -> 145000 | D7: =SUMIF(Register!$E$5:$E$30,$A7,Register!$L$5:$L$30) -> 12875
A8: All sources | B8: =SUM(B5:B7) -> 26 | C8: =SUM(C5:C7) -> 658816 | D8: =SUM(D5:D7) -> 96386.96
A10: Season One focus areas | B10: Sources | C10: Total ask ($) | D10: Expected ($)
A11: Students | B11: =COUNTIFS(Register!$D$5:$D$30,A11,Register!$E$5:$E$30,"Season One") -> 3 | C11: =SUMIFS(Register!$H$5:$H$30,Register!$D$5:$D$30,$A11,Register!$E$5:$E$30,"Season One") -> 25816 | D11: =SUMIFS(Register!$L$5:$L$30,Register!$D$5:$D$30,$A11,Register!$E$5:$E$30,"Season One") -> 13161.96
A12: Arts & culture | B12: =COUNTIFS(Register!$D$5:$D$30,A12,Register!$E$5:$E$30,"Season One") -> 3 | C12: =SUMIFS(Register!$H$5:$H$30,Register!$D$5:$D$30,$A12,Register!$E$5:$E$30,"Season One") -> 60000 | D12: =SUMIFS(Register!$L$5:$L$30,Register!$D$5:$D$30,$A12,Register!$E$5:$E$30,"Season One") -> 9900
A13: Community | B13: =COUNTIFS(Register!$D$5:$D$30,A13,Register!$E$5:$E$30,"Season One") -> 8 | C13: =SUMIFS(Register!$H$5:$H$30,Register!$D$5:$D$30,$A13,Register!$E$5:$E$30,"Season One") -> 146000 | D13: =SUMIFS(Register!$L$5:$L$30,Register!$D$5:$D$30,$A13,Register!$E$5:$E$30,"Season One") -> 27800
A14: Youth-led | B14: =COUNTIFS(Register!$D$5:$D$30,A14,Register!$E$5:$E$30,"Season One") -> 2 | C14: =SUMIFS(Register!$H$5:$H$30,Register!$D$5:$D$30,$A14,Register!$E$5:$E$30,"Season One") -> 7000 | D14: =SUMIFS(Register!$L$5:$L$30,Register!$D$5:$D$30,$A14,Register!$E$5:$E$30,"Season One") -> 1900
A16: Season One Target budget (from the budget workbook) | C16: 49730
A17: Season One expected outside funding | C17: =D5 -> 52761.96
A18: Shortfall to be covered by the McKenzie Towne Council partnership | C18: =MAX(0,C16-C17) -> 0
A20: Why 'expected' is far below 'ask': most funders won't give the full amount, and some won't fund us at all. Expected = Ask × chance of success × share typically awarded.
A21: Asking for the maximum needs a budget that justifies it. Several funders cap their share (e.g. City Tier 2 ≤ 50%, AFA ≤ 65%, Alberta government total ≤ 50%) and ask about other funding.
A22: If more arrives than Season One needs, the surplus scales the production up or is held, with funders' permission, for Season Two. The Council's match-contingent funds are then simply not drawn.
A23: Alberta Culture Days (up to $10,000) only applies if race weekend moves into September (3+ event days: Cubs' Quest, race night, premiere). Set its chance to 0% if the date stays in August.
A24: Charity-only funders (TELUS, Calgary Foundation Community Grants, Flames, Burns) need a registered-charity partner, such as a local church, school foundation or youth charity.

Sheet Register
A1: Funding Opportunities Register: The Wolf of McKenzie Towne
A2: Strategy: apply to every eligible source for its maximum. Expected = Ask × chance of success × share of ask typically awarded. Blue = editable inputs; yellow = judgement calls. Researched 20 October 2026; confirm every figure on the funder's own site.
A4: # | B4: Funder / program | C4: Level | D4: Focus | E4: Season | F4: Who can apply | G4: Maximum available ($) | H4: Our ask ($) | I4: Match / cost-share rule | J4: Chance of success | K4: Share of ask awarded | L4: Expected ($) | M4: Deadline / timing | N4: Next action | O4: Source
A5: 1 | B5: Canada Summer Jobs (2 summer production assistants, up to 16 weeks) | C5: Federal | D5: Students | E5: Season One | F5: Non-profit with CRA business number | G5: 18816 | H5: 18816 | I5: Non-profits: up to 100% of minimum wage + employment costs | J5: 0.7 | K5: 0.8 | L5: =H5*J5*K5 -> 10536.96 | M5: Opens 27 Oct 2026 (expected); closes ~3 Dec 2026 | N5: Apply on opening day; request the full 16 weeks for both positions | O5: https://www.canada.ca/en/employment-social-development/services/funding/canada-summer-jobs.html
A6: 2 | B6: Student Work Placement Program (co-op wage subsidy) | C6: Federal | D6: Students | E6: Season One | F6: Employer of a post-secondary co-op student | G6: 7000 | H6: 7000 | I6: 50% of wages up to $5,000; 70% up to $7,000 for under-represented students | J6: 0.5 | K6: 0.75 | L6: =H6*J6*K6 -> 2625 | M6: Year-round via delivery partners; first come | N6: Pick a delivery partner whose stream accepts marketing/event roles | O6: https://grantcompass.ca/student-work-placement-program-guide
A7: 3 | B7: Riipen Level UP (student project stipends, paid by Riipen) | C7: Federal-funded | D7: Students | E7: Season One | F7: Any organization (free) | G7: 0 | H7: 0 | I7: None. Riipen pays each student $1,400 directly (not cash to us) | J7: 0.8 | K7: 1 | L7: =H7*J7*K7 -> 0 | M7: Cohorts: 26 Oct–18 Dec 2026; 25 Jan–19 Mar 2027 | N7: Post 2 projects (sponsor deck, social campaign) for the January cohort | O7: https://help.riipen.com/en/articles/11140694-level-up-cohort-breakdown
A8: 4 | B8: Good Places (Federation of Calgary Communities) | C8: Municipal / Federation | D8: Community | E8: Season One | F8: Federation members; community associations get priority | G8: 15000 | H8: 15000 | I8: None stated | J8: 0.4 | K8: 0.6 | L8: =H8*J8*K8 -> 3600 | M8: Last 2026 round closes 30 Oct 2026 | N8: Apply now through a member community association, at the maximum | O8: https://goodplaces.calgarycommunities.com/grants/
A9: 5 | B9: Navacord Action Grants (Federation of Calgary Communities) | C9: Municipal / Federation | D9: Community | E9: Season One | F9: Federation members | G9: 1000 | H9: 1000 | I9: Reimbursement grant | J9: 0.3 | K9: 1 | L9: =H9*J9*K9 -> 300 | M9: Closes 31 Oct 2026 | N9: Quick application via the member association | O9: https://calgarycommunities.com/navacord-action-grants/
A10: 6 | B10: Neighbour Grants (Calgary Foundation) | C10: Foundation | D10: Community | E10: Season One | F10: Non-profits and charities (informal groups by discussion) | G10: 10000 | H10: 10000 | I10: None stated; artist fees eligible | J10: 0.5 | K10: 0.7 | L10: =H10*J10*K10 -> 3500 | M10: Next deadline listed 9 Nov 2026 (confirm) | N10: Call the Foundation, then apply at $10,000 | O10: https://calgaryfoundation.org/charities/grants/grassroots-grants/neighbour-grants/
A11: 7 | B11: Jim Button Youth Grant (Youth Central) | C11: Foundation | D11: Youth-led | E11: Season One | F11: Youth aged 12–18 (non-profit partner if no legal status) | G11: 2000 | H11: 2000 | I11: None stated | J11: 0.5 | K11: 1 | L11: =H11*J11*K11 -> 1000 | M11: Cycle 1 closes 28 Oct 2026 | N11: Youth Race Council applies, with the community association as partner | O11: https://youthcentral.com/program/grants/
A12: 8 | B12: Ward 12 Community Event Fund (City of Calgary) | C12: Municipal | D12: Community | E12: Season One | F12: Non-profits with their own bank account | G12: 20000 | H12: 10000 | I12: None. The councillor's annual pool is up to $20,000; first come, first served | J12: 0.5 | K12: 0.5 | L12: =H12*J12*K12 -> 2500 | M12: 2027 applications open 15 Dec 2026 | N12: Brief Councillor Jamieson's office in November; apply on 15 Dec | O12: https://www.calgary.ca/council/wardcommunityeventfund.html
A13: 9 | B13: Inspiring Neighbourhoods Grant (City of Calgary) | C13: Municipal | D13: Community | E13: Season One | F13: Community-based non-profits | G13: 15000 | H13: 15000 | I13: Applicant must match the full request (cash or eligible in-kind) | J13: 0.5 | K13: 0.6 | L13: =H13*J13*K13 -> 4500 | M13: Rolling, 2026 round open | N13: Apply under placemaking ($12,000–$15,000 cap) or engagement ($10,000); confirm category | O13: https://www.calgary.ca/social-services/funding/inspiring-neighbourhoods.html
A14: 10 | B14: Arts & Culture Microgrant, Tier 2 (City of Calgary) | C14: Municipal | D14: Arts & culture | E14: Season One | F14: Non-profits incl. community associations | G14: 30000 | H14: 30000 | I14: Covers up to 50% of project cost (Tier 1: up to $5,000 at 100%) | J14: 0.3 | K14: 0.5 | L14: =H14*J14*K14 -> 4500 | M14: 2027 intake expected ~March (unconfirmed) | N14: Frame the theatre production as the arts project; build a matching arts budget | O14: https://www.calgary.ca/arts-culture/microgrant.html
A15: 11 | B15: AFA Arts Presenting Project Funding (Alberta Foundation for the Arts) | C15: Provincial | D15: Arts & culture | E15: Season One | F15: Alberta non-profits presenting professional artists | G15: 20000 | H15: 20000 | I15: Up to 65% of project cost; cap unconfirmed (one AFA page lists $20,000) | J15: 0.25 | K15: 0.6 | L15: =H15*J15*K15 -> 3000 | M15: 1 Dec 2026 | N15: Present professional performers (e.g. Wagonstage) as the arts-presenting element | O15: https://hellodarwin.com/business-aid/programs/afa-arts-presenting-project-funding
A16: 12 | B16: Alberta Community Initiatives Program (CIP) Project Grant | C16: Provincial | D16: Community | E16: Season One | F16: Alberta non-profits, registered 1+ year | G16: 75000 | H16: 75000 | I16: Applicant must match at least the request; volunteer labour counts at $20–$40/hr; provincial share ≤ 50% | J16: 0.2 | K16: 0.5 | L16: =H16*J16*K16 -> 7500 | M16: 15 Feb 2027 intake (decision ~Aug 2027); also 15 Aug 2027 | N16: Apply 15 Feb 2027 at the maximum; if late, re-apply 15 Aug 2027 for Season Two | O16: https://www.alberta.ca/cip-project-grant
... A18: 14 | B18: Brookfield Residential (community's original developer) | C18: Corporate | D18: Community | E18: Season One | F18: Sponsorship request | G18: 10000 | H18: 10000 | I18: Sponsorship recognition | J18: 0.4 | K18: 0.6 | L18: =H18*J18*K18 -> 2400 | M18: Ask Jan–Mar 2027 | N18: Pitch the Presenting Sponsor tier; the village legacy story fits their brand | O18: https://www.brookfieldresidential.com/
A19: 15 | B19: High Street merchants and local businesses | C19: Corporate | D19: Community | E19: Season One | F19: Sponsorship tiers | G19: 10000 | H19: 10000 | I19: Sponsorship recognition | J19: 0.7 | K19: 0.5 | L19: =H19*J19*K19 -> 3500 | M19: Jan–May 2027 | N19: Youth Treasury Crew pitches with adult chaperones
A20: 16 | B20: Burns Memorial Fund (children and youth in low-income situations) | C20: Foundation | D20: Youth-led | E20: Season One | F20: Registered charities | G20: 15000 | H20: 5000 | I20: Bursary or access component only | J20: 0.3 | K20: 0.6 | L20: =H20*J20*K20 -> 900 | M20: Confirm 2027 dates | N20: Partner with a charity to fund bursaries and access | O20: https://burnsfund.com/
A21: 17 | B21: Canada Post Community Foundation | C21: Foundation | D21: Youth-led | E21: Season Two | F21: Registered charities and non-profits (youth up to 21) | G21: 25000 | H21: 25000 | I21: Must start or expand a service for children/youth | J21: 0.3 | K21: 0.7 | L21: =H21*J21*K21 -> 5250 | M21: Opens 8 Feb, closes 26 Feb 2027; announced Sept 2027 | N21: Apply Feb 2027 for Season Two youth-leadership programming | O21: https://www.canadapost-postescanada.ca/cpc/en/our-company/community-foundation/community-foundation-application.page
A22: 18 | B22: Building Communities through Arts & Heritage: Local Festivals (Canadian Heritage) | C22: Federal | D22: Arts & culture | E22: Season Two | F22: Local non-profits; must have run a prior edition | G22: 200000 | H22: 200000 | I22: Up to 100% of eligible expenses; first editions not eligible | J22: 0.3 | K22: 0.3 | L22: =H22*J22*K22 -> 18000 | M22: 15 Oct 2027 for summer 2028 festivals | N22: Run Season One well, then apply for Season Two as a recurring local arts festival | O22: https://hellodarwin.com/business-aid/programs/local-festivals-building-communities-through-arts-and-heritage
A23: 19 | B23: New Horizons for Seniors Program: community-based projects | C23: Federal | D23: Community | E23: Season Two | F23: Non-profits; projects led or inspired by seniors | G23: 50000 | H23: 50000 | I23: Up to $50,000 ($25,000 cap on capital) | J23: 0.25 | K23: 0.6 | L23: =H23*J23*K23 -> 7500 | M23: Next call expected ~June 2027 (2026 call: 2 Jun–14 Jul) | N23: Design an intergenerational strand: seniors as storytellers, porch captains and mentors | O23: https://www.canada.ca/en/employment-social-development/news/2026/06/new-horizons-for-seniors-program---call-for-proposals.html
A24: 20 | B24: TELUS Friendly Future Foundation: Calgary Community Board | C24: Corporate foundation | D24: Youth-led | E24: Partner route | F24: Registered charities only (youth up to 29) | G24: 20000 | H24: 20000 | I24: Single-year grant; one application per 12 months | J24: 0.25 | K24: 0.7 | L24: =H24*J24*K24 -> 3500 | M24: 2027 cycle TBA (2026 closed) | N24: Find a charity partner; watch for the 2027 cycle | O24: https://www.friendlyfuture.com/en/foundation/apply-for-funding
A25: 21 | B25: Calgary Foundation Community Grants | C25: Foundation | D25: Community | E25: Partner route | F25: Registered charities only | G25: 200000 | H25: 25000 | I25: Range about $5,000–$200,000 | J25: 0.25 | K25: 0.6 | L25: =H25*J25*K25 -> 3750 | M25: Typically mid-Feb and mid-Sept | N25: Charity partner required; target Season Two | O25: https://calgaryfoundation.org/
A26: 22 | B26: Calgary Flames Foundation Community Grants | C26: Corporate foundation | D26: Youth-led | E26: Partner route | F26: Registered charities (youth health, wellness, sport) | G26: 100000 | H26: 25000 | I26: Youth wellness focus | J26: 0.15 | K26: 0.5 | L26: =H26*J26*K26 -> 1875 | M26: ~1 Apr 2027 (confirm) | N26: Frame as youth wellness and activity; charity partner required | O26: https://hellodarwin.com/business-aid/programs/calgary-flames-foundation-community-grant-program
A27: 23 | B27: Canada Council for the Arts: Arts Across Canada, Public Outreach | C27: Federal | D27: Arts & culture | E27: Partner route | F27: Arts groups and organizations only | G27: 75000 | H27: 25000 | I27: Professional arts eligibility required | J27: 0.1 | K27: 0.5 | L27: =H27*J27*K27 -> 1250 | M27: Next published deadline passed 14 Oct 2026; check the next one | N27: Only via an eligible arts partner (e.g. a theatre company co-producing) | O27: https://canadacouncil.ca/funding/grants/arts-across-canada-and-abroad
A28: 24 | B28: Canadian Heritage: Youth Take Charge / Youth Engagement Program | C28: Federal | D28: Youth-led | E28: Partner route | F28: Non-profits with 3+ years of youth programming | G28: 500000 | H28: 50000 | I28: Total federal assistance ≤ 75% of costs | J28: 0.1 | K28: 0.5 | L28: =H28*J28*K28 -> 2500 | M28: Closed; next intake TBA | N28: Only through a partner with a youth-programming track record (e.g. a youth organization) | O28: https://hellodarwin.com/business-aid/programs/youth-take-charge
A29: 25 | B29: Young Canada Works (heritage organizations) | C29: Federal | D29: Students | E29: Partner route | F29: Heritage organizations | G29: 10000 | H29: 0 | I29: About 50% of wages | J29: 0 | K29: 0 | L29: =H29*J29*K29 -> 0 | M29: 15 Jan 2027 | N29: Not a fit unless a heritage organization co-hosts | O29: https://www.canada.ca/en/canadian-heritage/services/funding/young-canada-works/employers.html
A30: 26 | B30: Canada Service Corps (youth service) | C30: Federal | D30: Youth-led | E30: Partner route | F30: Funded organizations only | G30: 5000 | H30: 0 | I30: Micro-grants through funded organizations | J30: 0 | K30: 0 | L30: =H30*J30*K30 -> 0 | M30: No open intake found | N30: Monitor; no action now | O30: https://www.canada.ca/en/employment-social-development/services/funding/microgrants-youth-organizations.html
B31: Totals (all rows) | H31: =SUM(H5:H30) -> 658816 | L31: =SUM(L5:L30) -> 96386.96
